LICENSE
MANIFEST.in
README.md
package.json
setup.py
select_filter/CardDropdown.py
select_filter/DateFilter.py
select_filter/RadioFilter.py
select_filter/SelectFilter.py
select_filter/TimeGrainFilter.py
select_filter/__init__.py
select_filter/_imports_.py
select_filter/metadata.json
select_filter/package-info.json
select_filter/select_filter.min.js
select_filter/select_filter.min.js.map
select_filter.egg-info/PKG-INFO
select_filter.egg-info/SOURCES.txt
select_filter.egg-info/dependency_links.txt
select_filter.egg-info/top_level.txt