Metadata-Version: 2.1
Name: select-filter
Version: 0.0.17
Summary: the selected date filter
Home-page: UNKNOWN
Author: kalimuthu periyasamy <1995kalimuthu@gmail.com>
License: MIT
Platform: UNKNOWN
Classifier: Framework :: Dash
License-File: LICENSE
